{
  "openapi": "3.1.0",
  "info": {
    "title": "zxcv - Rule Management API",
    "version": "1.0.0",
    "description": "API for managing and sharing coding rules and guidelines"
  },
  "components": {
    "schemas": {},
    "parameters": {}
  },
  "paths": {
    "/api-keys": {
      "post": {
        "tags": [
          "API Keys"
        ],
        "summary": "Create a new API key",
        "security": [
          {
            "bearerAuth": []
          }
        ],
        "operationId": "post_CreateApiKeyEndpoint",
        "requestBody": {
          "content": {
            "application/json": {
              "schema": {
                "type": "object",
                "properties": {
                  "name": {
                    "type": "string",
                    "minLength": 1,
                    "maxLength": 100
                  },
                  "scopes": {
                    "type": "array",
                    "items": {
                      "type": "string",
                      "enum": [
                        "rules:read",
                        "rules:write",
                        "teams:read",
                        "teams:write",
                        "users:read",
                        "users:write",
                        "api_keys:read",
                        "api_keys:write"
                      ]
                    }
                  },
                  "expires_at": {
                    "type": "number"
                  }
                },
                "required": [
                  "name"
                ]
              }
            }
          }
        },
        "responses": {
          "201": {
            "description": "API key created successfully",
            "content": {
              "application/json": {
                "schema": {
                  "type": "object",
                  "properties": {
                    "id": {
                      "type": "string"
                    },
                    "name": {
                      "type": "string"
                    },
                    "key": {
                      "type": "string"
                    },
                    "scopes": {
                      "type": "array",
                      "items": {
                        "type": "string"
                      }
                    },
                    "expires_at": {
                      "type": [
                        "number",
                        "null"
                      ]
                    },
                    "created_at": {
                      "type": "number"
                    }
                  },
                  "required": [
                    "id",
                    "name",
                    "key",
                    "scopes",
                    "expires_at",
                    "created_at"
                  ]
                }
              }
            }
          },
          "400": {
            "description": "Invalid input data"
          },
          "401": {
            "description": "Authentication required"
          }
        }
      },
      "get": {
        "tags": [
          "API Keys"
        ],
        "summary": "Get user's API keys",
        "security": [
          {
            "bearerAuth": []
          }
        ],
        "operationId": "get_GetApiKeysEndpoint",
        "parameters": [
          {
            "schema": {
              "type": "string",
              "default": "20"
            },
            "required": false,
            "name": "limit",
            "in": "query"
          },
          {
            "schema": {
              "type": "string",
              "default": "0"
            },
            "required": false,
            "name": "offset",
            "in": "query"
          }
        ],
        "responses": {
          "200": {
            "description": "API keys retrieved successfully",
            "content": {
              "application/json": {
                "schema": {
                  "type": "object",
                  "properties": {
                    "results": {
                      "type": "array",
                      "items": {
                        "type": "object",
                        "properties": {
                          "id": {
                            "type": "string"
                          },
                          "name": {
                            "type": "string"
                          },
                          "scopes": {
                            "type": "array",
                            "items": {
                              "type": "string"
                            }
                          },
                          "expires_at": {
                            "type": [
                              "number",
                              "null"
                            ]
                          },
                          "last_used_at": {
                            "type": [
                              "number",
                              "null"
                            ]
                          },
                          "created_at": {
                            "type": "number"
                          }
                        },
                        "required": [
                          "id",
                          "name",
                          "scopes",
                          "expires_at",
                          "last_used_at",
                          "created_at"
                        ]
                      }
                    },
                    "total": {
                      "type": "number"
                    },
                    "limit": {
                      "type": "number"
                    },
                    "offset": {
                      "type": "number"
                    }
                  },
                  "required": [
                    "results",
                    "total",
                    "limit",
                    "offset"
                  ]
                }
              }
            }
          },
          "401": {
            "description": "Authentication required"
          }
        }
      }
    },
    "/api-keys/{id}": {
      "delete": {
        "tags": [
          "API Keys"
        ],
        "summary": "Delete an API key",
        "security": [
          {
            "bearerAuth": []
          }
        ],
        "operationId": "delete_DeleteApiKeyEndpoint",
        "parameters": [
          {
            "schema": {
              "type": "string"
            },
            "required": true,
            "name": "id",
            "in": "path"
          }
        ],
        "responses": {
          "204": {
            "description": "API key deleted successfully"
          },
          "401": {
            "description": "Authentication required"
          },
          "404": {
            "description": "API key not found"
          }
        }
      },
      "put": {
        "tags": [
          "API Keys"
        ],
        "summary": "Update an API key",
        "security": [
          {
            "bearerAuth": []
          }
        ],
        "operationId": "put_UpdateApiKeyEndpoint",
        "parameters": [
          {
            "schema": {
              "type": "string"
            },
            "required": true,
            "name": "id",
            "in": "path"
          }
        ],
        "requestBody": {
          "content": {
            "application/json": {
              "schema": {
                "type": "object",
                "properties": {
                  "name": {
                    "type": "string",
                    "minLength": 1,
                    "maxLength": 100
                  },
                  "scopes": {
                    "type": "array",
                    "items": {
                      "type": "string"
                    }
                  },
                  "expires_at": {
                    "type": "number"
                  }
                }
              }
            }
          }
        },
        "responses": {
          "200": {
            "description": "API key updated successfully",
            "content": {
              "application/json": {
                "schema": {
                  "type": "object",
                  "properties": {
                    "id": {
                      "type": "string"
                    },
                    "name": {
                      "type": "string"
                    },
                    "scopes": {
                      "type": "array",
                      "items": {
                        "type": "string"
                      }
                    },
                    "expires_at": {
                      "type": [
                        "number",
                        "null"
                      ]
                    },
                    "last_used_at": {
                      "type": [
                        "number",
                        "null"
                      ]
                    },
                    "created_at": {
                      "type": "number"
                    }
                  },
                  "required": [
                    "id",
                    "name",
                    "scopes",
                    "expires_at",
                    "last_used_at",
                    "created_at"
                  ]
                }
              }
            }
          },
          "400": {
            "description": "Invalid input data"
          },
          "401": {
            "description": "Authentication required"
          },
          "404": {
            "description": "API key not found"
          }
        }
      }
    },
    "/auth/register": {
      "post": {
        "tags": [
          "Auth"
        ],
        "summary": "Register a new user",
        "operationId": "post_RegisterEndpoint",
        "requestBody": {
          "content": {
            "application/json": {
              "schema": {
                "type": "object",
                "properties": {
                  "email": {
                    "type": "string",
                    "format": "email"
                  },
                  "username": {
                    "type": "string",
                    "minLength": 3,
                    "maxLength": 20,
                    "pattern": "^[a-zA-Z0-9_-]+$"
                  },
                  "password": {
                    "type": "string",
                    "minLength": 8
                  }
                },
                "required": [
                  "email",
                  "username",
                  "password"
                ]
              }
            }
          }
        },
        "responses": {
          "201": {
            "description": "User created successfully",
            "content": {
              "application/json": {
                "schema": {
                  "type": "object",
                  "properties": {
                    "token": {
                      "type": "string"
                    },
                    "refreshToken": {
                      "type": "string"
                    },
                    "user": {
                      "type": "object",
                      "properties": {
                        "id": {
                          "type": "string"
                        },
                        "email": {
                          "type": "string"
                        },
                        "username": {
                          "type": "string"
                        }
                      },
                      "required": [
                        "id",
                        "email",
                        "username"
                      ]
                    }
                  },
                  "required": [
                    "token",
                    "refreshToken",
                    "user"
                  ]
                }
              }
            }
          },
          "409": {
            "description": "User already exists"
          }
        }
      }
    },
    "/auth/login": {
      "post": {
        "tags": [
          "Auth"
        ],
        "summary": "Login with email and password",
        "operationId": "post_LoginEndpoint",
        "requestBody": {
          "content": {
            "application/json": {
              "schema": {
                "type": "object",
                "properties": {
                  "email": {
                    "type": "string",
                    "format": "email"
                  },
                  "password": {
                    "type": "string"
                  }
                },
                "required": [
                  "email",
                  "password"
                ]
              }
            }
          }
        },
        "responses": {
          "200": {
            "description": "Login successful",
            "content": {
              "application/json": {
                "schema": {
                  "type": "object",
                  "properties": {
                    "token": {
                      "type": "string"
                    },
                    "refreshToken": {
                      "type": "string"
                    },
                    "user": {
                      "type": "object",
                      "properties": {
                        "id": {
                          "type": "string"
                        },
                        "email": {
                          "type": "string"
                        },
                        "username": {
                          "type": "string"
                        }
                      },
                      "required": [
                        "id",
                        "email",
                        "username"
                      ]
                    }
                  },
                  "required": [
                    "token",
                    "refreshToken",
                    "user"
                  ]
                }
              }
            }
          },
          "401": {
            "description": "Invalid credentials"
          }
        }
      }
    },
    "/auth/logout": {
      "post": {
        "tags": [
          "Auth"
        ],
        "summary": "Logout user",
        "operationId": "post_LogoutEndpoint",
        "requestBody": {
          "content": {
            "application/json": {
              "schema": {
                "type": "object",
                "properties": {
                  "refreshToken": {
                    "type": "string"
                  }
                },
                "required": [
                  "refreshToken"
                ]
              }
            }
          }
        },
        "responses": {
          "200": {
            "description": "Successfully logged out",
            "content": {
              "application/json": {
                "schema": {
                  "type": "object",
                  "properties": {
                    "success": {
                      "type": "boolean"
                    },
                    "message": {
                      "type": "string"
                    }
                  },
                  "required": [
                    "success",
                    "message"
                  ]
                }
              }
            }
          },
          "401": {
            "description": "Invalid refresh token"
          }
        }
      }
    },
    "/auth/refresh": {
      "post": {
        "tags": [
          "Auth"
        ],
        "summary": "Refresh access token",
        "operationId": "post_RefreshTokenEndpoint",
        "requestBody": {
          "content": {
            "application/json": {
              "schema": {
                "type": "object",
                "properties": {
                  "refreshToken": {
                    "type": "string"
                  }
                },
                "required": [
                  "refreshToken"
                ]
              }
            }
          }
        },
        "responses": {
          "200": {
            "description": "Token refreshed successfully",
            "content": {
              "application/json": {
                "schema": {
                  "type": "object",
                  "properties": {
                    "token": {
                      "type": "string"
                    },
                    "user": {
                      "type": "object",
                      "properties": {
                        "id": {
                          "type": "string"
                        },
                        "email": {
                          "type": "string"
                        },
                        "username": {
                          "type": "string"
                        }
                      },
                      "required": [
                        "id",
                        "email",
                        "username"
                      ]
                    }
                  },
                  "required": [
                    "token",
                    "user"
                  ]
                }
              }
            }
          },
          "401": {
            "description": "Invalid refresh token"
          }
        }
      }
    },
    "/auth/forgot-password": {
      "post": {
        "tags": [
          "Auth"
        ],
        "summary": "Request password reset",
        "operationId": "post_ForgotPasswordEndpoint",
        "requestBody": {
          "content": {
            "application/json": {
              "schema": {
                "type": "object",
                "properties": {
                  "email": {
                    "type": "string",
                    "format": "email"
                  }
                },
                "required": [
                  "email"
                ]
              }
            }
          }
        },
        "responses": {
          "200": {
            "description": "Password reset email sent",
            "content": {
              "application/json": {
                "schema": {
                  "type": "object",
                  "properties": {
                    "message": {
                      "type": "string"
                    }
                  },
                  "required": [
                    "message"
                  ]
                }
              }
            }
          }
        }
      }
    },
    "/auth/reset-password": {
      "post": {
        "tags": [
          "Auth"
        ],
        "summary": "Reset password with token",
        "operationId": "post_ResetPasswordEndpoint",
        "requestBody": {
          "content": {
            "application/json": {
              "schema": {
                "type": "object",
                "properties": {
                  "token": {
                    "type": "string"
                  },
                  "newPassword": {
                    "type": "string",
                    "minLength": 8
                  }
                },
                "required": [
                  "token",
                  "newPassword"
                ]
              }
            }
          }
        },
        "responses": {
          "200": {
            "description": "Password reset successfully",
            "content": {
              "application/json": {
                "schema": {
                  "type": "object",
                  "properties": {
                    "message": {
                      "type": "string"
                    }
                  },
                  "required": [
                    "message"
                  ]
                }
              }
            }
          },
          "400": {
            "description": "Invalid or expired token"
          }
        }
      }
    },
    "/rules/search": {
      "get": {
        "tags": [
          "Rules",
          "Search"
        ],
        "summary": "Search rules",
        "security": [
          {
            "bearerAuth": []
          }
        ],
        "operationId": "get_SearchRulesEndpoint",
        "parameters": [
          {
            "schema": {
              "type": "string"
            },
            "required": false,
            "name": "q",
            "in": "query"
          },
          {
            "schema": {
              "type": "string"
            },
            "required": false,
            "name": "tags",
            "in": "query"
          },
          {
            "schema": {
              "type": "string"
            },
            "required": false,
            "name": "author",
            "in": "query"
          },
          {
            "schema": {
              "type": "string"
            },
            "required": false,
            "name": "org",
            "in": "query"
          },
          {
            "schema": {
              "type": "string",
              "enum": [
                "public",
                "private",
                "team",
                "all"
              ],
              "default": "all"
            },
            "required": false,
            "name": "visibility",
            "in": "query"
          },
          {
            "schema": {
              "type": "string",
              "enum": [
                "relevance",
                "updated",
                "created",
                "name"
              ],
              "default": "relevance"
            },
            "required": false,
            "name": "sort",
            "in": "query"
          },
          {
            "schema": {
              "type": "string",
              "enum": [
                "asc",
                "desc"
              ],
              "default": "desc"
            },
            "required": false,
            "name": "order",
            "in": "query"
          },
          {
            "schema": {
              "type": "number",
              "minimum": 1,
              "maximum": 100,
              "default": 20
            },
            "required": false,
            "name": "limit",
            "in": "query"
          },
          {
            "schema": {
              "type": "number",
              "minimum": 0,
              "default": 0
            },
            "required": false,
            "name": "offset",
            "in": "query"
          }
        ],
        "responses": {
          "200": {
            "description": "Search results",
            "content": {
              "application/json": {
                "schema": {
                  "type": "object",
                  "properties": {
                    "results": {
                      "type": "array",
                      "items": {
                        "type": "object",
                        "properties": {
                          "id": {
                            "type": "string"
                          },
                          "name": {
                            "type": "string"
                          },
                          "org": {
                            "type": "string"
                          },
                          "visibility": {
                            "type": "string"
                          },
                          "description": {
                            "type": "string"
                          },
                          "tags": {
                            "type": "array",
                            "items": {
                              "type": "string"
                            }
                          },
                          "version": {
                            "type": "string"
                          },
                          "author": {
                            "type": "object",
                            "properties": {
                              "id": {
                                "type": "string"
                              },
                              "username": {
                                "type": "string"
                              }
                            },
                            "required": [
                              "id",
                              "username"
                            ]
                          },
                          "created_at": {
                            "type": "number"
                          },
                          "updated_at": {
                            "type": "number"
                          }
                        },
                        "required": [
                          "id",
                          "name",
                          "visibility",
                          "version",
                          "author",
                          "created_at",
                          "updated_at"
                        ]
                      }
                    },
                    "total": {
                      "type": "number"
                    },
                    "limit": {
                      "type": "number"
                    },
                    "offset": {
                      "type": "number"
                    }
                  },
                  "required": [
                    "results",
                    "total",
                    "limit",
                    "offset"
                  ]
                }
              }
            }
          }
        }
      }
    },
    "/rules": {
      "post": {
        "tags": [
          "Rules"
        ],
        "summary": "Create a new rule",
        "security": [
          {
            "bearerAuth": []
          }
        ],
        "operationId": "post_CreateRuleEndpoint",
        "requestBody": {
          "content": {
            "application/json": {
              "schema": {
                "type": "object",
                "properties": {
                  "name": {
                    "type": "string",
                    "minLength": 1,
                    "maxLength": 100,
                    "pattern": "^[a-zA-Z0-9_-]+$"
                  },
                  "org": {
                    "type": "string",
                    "minLength": 1,
                    "maxLength": 50,
                    "pattern": "^[a-zA-Z0-9_-]+$"
                  },
                  "visibility": {
                    "type": "string",
                    "enum": [
                      "public",
                      "private",
                      "team"
                    ],
                    "default": "private"
                  },
                  "description": {
                    "type": "string",
                    "maxLength": 500
                  },
                  "tags": {
                    "type": "array",
                    "items": {
                      "type": "string"
                    }
                  },
                  "content": {
                    "type": "string",
                    "minLength": 1
                  }
                },
                "required": [
                  "name",
                  "content"
                ]
              }
            }
          }
        },
        "responses": {
          "201": {
            "description": "Rule created successfully",
            "content": {
              "application/json": {
                "schema": {
                  "type": "object",
                  "properties": {
                    "id": {
                      "type": "string"
                    },
                    "name": {
                      "type": "string"
                    },
                    "org": {
                      "type": "string"
                    },
                    "visibility": {
                      "type": "string"
                    },
                    "version": {
                      "type": "string"
                    },
                    "created_at": {
                      "type": "number"
                    }
                  },
                  "required": [
                    "id",
                    "name",
                    "visibility",
                    "version",
                    "created_at"
                  ]
                }
              }
            }
          },
          "401": {
            "description": "Unauthorized"
          },
          "409": {
            "description": "Rule already exists"
          }
        }
      }
    },
    "/rules/@{org}/{rulename}": {
      "get": {
        "tags": [
          "Rules"
        ],
        "summary": "Get a rule by organization and name",
        "security": [
          {
            "bearerAuth": []
          }
        ],
        "operationId": "get_GetOrgRuleEndpoint",
        "parameters": [
          {
            "schema": {
              "type": "string"
            },
            "required": true,
            "name": "org",
            "in": "path"
          },
          {
            "schema": {
              "type": "string"
            },
            "required": true,
            "name": "rulename",
            "in": "path"
          },
          {
            "schema": {
              "type": "string"
            },
            "required": false,
            "name": "version",
            "in": "query"
          }
        ],
        "responses": {
          "200": {
            "description": "Rule retrieved successfully",
            "content": {
              "application/json": {
                "schema": {
                  "type": "object",
                  "properties": {
                    "id": {
                      "type": "string"
                    },
                    "name": {
                      "type": "string"
                    },
                    "organization": {
                      "type": "string"
                    },
                    "visibility": {
                      "type": "string"
                    },
                    "description": {
                      "type": "string"
                    },
                    "tags": {
                      "type": "array",
                      "items": {
                        "type": "string"
                      }
                    },
                    "version": {
                      "type": "string"
                    },
                    "content": {
                      "type": "string"
                    },
                    "author": {
                      "type": "object",
                      "properties": {
                        "id": {
                          "type": "string"
                        },
                        "username": {
                          "type": "string"
                        }
                      },
                      "required": [
                        "id",
                        "username"
                      ]
                    },
                    "created_at": {
                      "type": "number"
                    },
                    "updated_at": {
                      "type": "number"
                    }
                  },
                  "required": [
                    "id",
                    "name",
                    "organization",
                    "visibility",
                    "version",
                    "content",
                    "author",
                    "created_at",
                    "updated_at"
                  ]
                }
              }
            }
          },
          "401": {
            "description": "Unauthorized"
          },
          "404": {
            "description": "Rule not found"
          }
        }
      }
    },
    "/rules/{rulename}": {
      "get": {
        "tags": [
          "Rules"
        ],
        "summary": "Get a rule by name or organization/name",
        "security": [
          {
            "bearerAuth": []
          }
        ],
        "operationId": "get_GetRuleEndpoint",
        "parameters": [
          {
            "schema": {
              "type": "string"
            },
            "required": true,
            "name": "rulename",
            "in": "path"
          },
          {
            "schema": {
              "type": "string"
            },
            "required": false,
            "name": "org",
            "in": "query"
          },
          {
            "schema": {
              "type": "string"
            },
            "required": false,
            "name": "version",
            "in": "query"
          }
        ],
        "responses": {
          "200": {
            "description": "Rule retrieved successfully",
            "content": {
              "application/json": {
                "schema": {
                  "type": "object",
                  "properties": {
                    "id": {
                      "type": "string"
                    },
                    "name": {
                      "type": "string"
                    },
                    "org": {
                      "type": "string"
                    },
                    "visibility": {
                      "type": "string"
                    },
                    "description": {
                      "type": "string"
                    },
                    "tags": {
                      "type": "array",
                      "items": {
                        "type": "string"
                      }
                    },
                    "version": {
                      "type": "string"
                    },
                    "content": {
                      "type": "string"
                    },
                    "author": {
                      "type": "object",
                      "properties": {
                        "id": {
                          "type": "string"
                        },
                        "username": {
                          "type": "string"
                        }
                      },
                      "required": [
                        "id",
                        "username"
                      ]
                    },
                    "created_at": {
                      "type": "number"
                    },
                    "updated_at": {
                      "type": "number"
                    }
                  },
                  "required": [
                    "id",
                    "name",
                    "visibility",
                    "version",
                    "content",
                    "author",
                    "created_at",
                    "updated_at"
                  ]
                }
              }
            }
          },
          "401": {
            "description": "Unauthorized"
          },
          "404": {
            "description": "Rule not found"
          }
        }
      }
    },
    "/rules/{id}": {
      "put": {
        "tags": [
          "Rules"
        ],
        "summary": "Update an existing rule",
        "security": [
          {
            "bearerAuth": []
          }
        ],
        "operationId": "put_UpdateRuleEndpoint",
        "parameters": [
          {
            "schema": {
              "type": "string"
            },
            "required": true,
            "name": "id",
            "in": "path"
          }
        ],
        "requestBody": {
          "content": {
            "application/json": {
              "schema": {
                "type": "object",
                "properties": {
                  "description": {
                    "type": "string",
                    "maxLength": 500
                  },
                  "tags": {
                    "type": "array",
                    "items": {
                      "type": "string"
                    }
                  },
                  "content": {
                    "type": "string"
                  },
                  "version": {
                    "type": "string",
                    "pattern": "^\\d+\\.\\d+\\.\\d+$"
                  },
                  "changelog": {
                    "type": "string"
                  }
                }
              }
            }
          }
        },
        "responses": {
          "200": {
            "description": "Rule updated successfully",
            "content": {
              "application/json": {
                "schema": {
                  "type": "object",
                  "properties": {
                    "id": {
                      "type": "string"
                    },
                    "version": {
                      "type": "string"
                    },
                    "updated_at": {
                      "type": "number"
                    }
                  },
                  "required": [
                    "id",
                    "version",
                    "updated_at"
                  ]
                }
              }
            }
          },
          "401": {
            "description": "Unauthorized"
          },
          "404": {
            "description": "Rule not found"
          }
        }
      },
      "delete": {
        "tags": [
          "Rules"
        ],
        "summary": "Delete a rule",
        "security": [
          {
            "bearerAuth": []
          }
        ],
        "operationId": "delete_DeleteRuleEndpoint",
        "parameters": [
          {
            "schema": {
              "type": "string"
            },
            "required": true,
            "name": "id",
            "in": "path"
          }
        ],
        "responses": {
          "204": {
            "description": "Rule deleted successfully"
          },
          "401": {
            "description": "Unauthorized"
          },
          "404": {
            "description": "Rule not found"
          }
        }
      }
    },
    "/rules/{id}/publish": {
      "post": {
        "tags": [
          "Rules"
        ],
        "summary": "Publish a new version of a rule",
        "security": [
          {
            "bearerAuth": []
          }
        ],
        "operationId": "post_PublishRuleEndpoint",
        "parameters": [
          {
            "schema": {
              "type": "string"
            },
            "required": true,
            "name": "id",
            "in": "path"
          }
        ],
        "requestBody": {
          "content": {
            "application/json": {
              "schema": {
                "type": "object",
                "properties": {
                  "version": {
                    "type": "string",
                    "pattern": "^\\d+\\.\\d+\\.\\d+$"
                  },
                  "changelog": {
                    "type": "string"
                  },
                  "content": {
                    "type": "string",
                    "minLength": 1
                  }
                },
                "required": [
                  "version",
                  "content"
                ]
              }
            }
          }
        },
        "responses": {
          "200": {
            "description": "Rule published successfully",
            "content": {
              "application/json": {
                "schema": {
                  "type": "object",
                  "properties": {
                    "id": {
                      "type": "string"
                    },
                    "version": {
                      "type": "string"
                    },
                    "published_at": {
                      "type": "number"
                    }
                  },
                  "required": [
                    "id",
                    "version",
                    "published_at"
                  ]
                }
              }
            }
          },
          "403": {
            "description": "Forbidden"
          },
          "404": {
            "description": "Rule not found"
          }
        }
      }
    },
    "/rules/{id}/visibility": {
      "put": {
        "tags": [
          "Rules"
        ],
        "summary": "Change rule visibility (public/private/team)",
        "security": [
          {
            "bearerAuth": []
          }
        ],
        "operationId": "put_ChangeVisibilityEndpoint",
        "parameters": [
          {
            "schema": {
              "type": "string"
            },
            "required": true,
            "name": "id",
            "in": "path"
          }
        ],
        "requestBody": {
          "content": {
            "application/json": {
              "schema": {
                "type": "object",
                "properties": {
                  "visibility": {
                    "type": "string",
                    "enum": [
                      "public",
                      "private",
                      "team"
                    ]
                  },
                  "teamId": {
                    "type": "string"
                  }
                },
                "required": [
                  "visibility"
                ]
              }
            }
          }
        },
        "responses": {
          "200": {
            "description": "Visibility changed successfully",
            "content": {
              "application/json": {
                "schema": {
                  "type": "object",
                  "properties": {
                    "id": {
                      "type": "string"
                    },
                    "visibility": {
                      "type": "string"
                    },
                    "updated_at": {
                      "type": "number"
                    }
                  },
                  "required": [
                    "id",
                    "visibility",
                    "updated_at"
                  ]
                }
              }
            }
          },
          "400": {
            "description": "Bad request"
          },
          "401": {
            "description": "Unauthorized"
          },
          "404": {
            "description": "Rule not found"
          }
        }
      }
    },
    "/rules/{id}/star": {
      "post": {
        "tags": [
          "Rules"
        ],
        "summary": "Star or unstar a rule",
        "security": [
          {
            "bearerAuth": []
          }
        ],
        "operationId": "post_StarRuleEndpoint",
        "parameters": [
          {
            "schema": {
              "type": "string"
            },
            "required": true,
            "name": "id",
            "in": "path"
          }
        ],
        "requestBody": {
          "content": {
            "application/json": {
              "schema": {
                "type": "object",
                "properties": {
                  "star": {
                    "type": "boolean"
                  }
                },
                "required": [
                  "star"
                ]
              }
            }
          }
        },
        "responses": {
          "200": {
            "description": "Star status updated",
            "content": {
              "application/json": {
                "schema": {
                  "type": "object",
                  "properties": {
                    "starred": {
                      "type": "boolean"
                    },
                    "stars": {
                      "type": "number"
                    }
                  },
                  "required": [
                    "starred",
                    "stars"
                  ]
                }
              }
            }
          },
          "401": {
            "description": "Unauthorized"
          },
          "404": {
            "description": "Rule not found"
          }
        }
      }
    },
    "/rules/{id}/download": {
      "get": {
        "tags": [
          "Rules"
        ],
        "summary": "Download a rule content",
        "security": [],
        "operationId": "get_DownloadRuleEndpoint",
        "parameters": [
          {
            "schema": {
              "type": "string"
            },
            "required": true,
            "name": "id",
            "in": "path"
          },
          {
            "schema": {
              "type": "string"
            },
            "required": false,
            "name": "version",
            "in": "query"
          },
          {
            "schema": {
              "type": "string",
              "enum": [
                "markdown",
                "text",
                "json"
              ],
              "default": "markdown"
            },
            "required": false,
            "name": "format",
            "in": "query"
          }
        ],
        "responses": {
          "200": {
            "description": "Rule content",
            "content": {
              "text/markdown": {
                "schema": {
                  "type": "string"
                }
              },
              "text/plain": {
                "schema": {
                  "type": "string"
                }
              },
              "application/json": {
                "schema": {
                  "type": "object",
                  "properties": {
                    "id": {
                      "type": "string"
                    },
                    "name": {
                      "type": "string"
                    },
                    "version": {
                      "type": "string"
                    },
                    "content": {
                      "type": "string"
                    },
                    "metadata": {
                      "type": "object",
                      "properties": {
                        "org": {
                          "type": "string"
                        },
                        "description": {
                          "type": "string"
                        },
                        "tags": {
                          "type": "array",
                          "items": {
                            "type": "string"
                          }
                        },
                        "author": {
                          "type": "string"
                        },
                        "created_at": {
                          "type": "number"
                        },
                        "updated_at": {
                          "type": "number"
                        }
                      },
                      "required": [
                        "author",
                        "created_at",
                        "updated_at"
                      ]
                    }
                  },
                  "required": [
                    "id",
                    "name",
                    "version",
                    "content",
                    "metadata"
                  ]
                }
              }
            }
          },
          "401": {
            "description": "Unauthorized"
          },
          "404": {
            "description": "Rule not found"
          }
        }
      }
    },
    "/rules/{id}/copy": {
      "post": {
        "tags": [
          "Rules"
        ],
        "summary": "Copy an existing rule",
        "security": [
          {
            "bearerAuth": []
          }
        ],
        "operationId": "post_CopyRuleEndpoint",
        "parameters": [
          {
            "schema": {
              "type": "string"
            },
            "required": true,
            "name": "id",
            "in": "path"
          }
        ],
        "requestBody": {
          "content": {
            "application/json": {
              "schema": {
                "type": "object",
                "properties": {
                  "name": {
                    "type": "string",
                    "minLength": 1,
                    "maxLength": 100,
                    "pattern": "^[a-zA-Z0-9_-]+$"
                  },
                  "org": {
                    "type": "string",
                    "minLength": 1,
                    "maxLength": 50,
                    "pattern": "^[a-zA-Z0-9_-]+$"
                  },
                  "visibility": {
                    "type": "string",
                    "enum": [
                      "public",
                      "private",
                      "team"
                    ],
                    "default": "private"
                  },
                  "team_id": {
                    "type": "string"
                  }
                },
                "required": [
                  "name"
                ]
              }
            }
          }
        },
        "responses": {
          "201": {
            "description": "Rule copied successfully",
            "content": {
              "application/json": {
                "schema": {
                  "type": "object",
                  "properties": {
                    "id": {
                      "type": "string"
                    },
                    "name": {
                      "type": "string"
                    },
                    "org": {
                      "type": "string"
                    },
                    "visibility": {
                      "type": "string"
                    },
                    "version": {
                      "type": "string"
                    },
                    "created_at": {
                      "type": "number"
                    }
                  },
                  "required": [
                    "id",
                    "name",
                    "visibility",
                    "version",
                    "created_at"
                  ]
                }
              }
            }
          },
          "401": {
            "description": "Unauthorized"
          },
          "404": {
            "description": "Rule not found"
          },
          "409": {
            "description": "Rule already exists"
          }
        }
      }
    },
    "/rules/{id}/versions": {
      "get": {
        "tags": [
          "Rules",
          "Versions"
        ],
        "summary": "Get version history of a rule",
        "security": [
          {
            "bearerAuth": []
          }
        ],
        "operationId": "get_GetVersionsEndpoint",
        "parameters": [
          {
            "schema": {
              "type": "string"
            },
            "required": true,
            "name": "id",
            "in": "path"
          }
        ],
        "responses": {
          "200": {
            "description": "Version history retrieved successfully",
            "content": {
              "application/json": {
                "schema": {
                  "type": "object",
                  "properties": {
                    "versions": {
                      "type": "array",
                      "items": {
                        "type": "object",
                        "properties": {
                          "id": {
                            "type": "string"
                          },
                          "version_number": {
                            "type": "string"
                          },
                          "changelog": {
                            "type": "string"
                          },
                          "created_at": {
                            "type": "number"
                          },
                          "created_by": {
                            "type": "object",
                            "properties": {
                              "id": {
                                "type": "string"
                              },
                              "username": {
                                "type": "string"
                              }
                            },
                            "required": [
                              "id",
                              "username"
                            ]
                          }
                        },
                        "required": [
                          "id",
                          "version_number",
                          "created_at",
                          "created_by"
                        ]
                      }
                    }
                  },
                  "required": [
                    "versions"
                  ]
                }
              }
            }
          },
          "401": {
            "description": "Unauthorized"
          },
          "404": {
            "description": "Rule not found"
          }
        }
      }
    },
    "/rules/{id}/versions/{version}": {
      "get": {
        "tags": [
          "Rules",
          "Versions"
        ],
        "summary": "Get a specific version of a rule",
        "security": [
          {
            "bearerAuth": []
          }
        ],
        "operationId": "get_GetSpecificVersionEndpoint",
        "parameters": [
          {
            "schema": {
              "type": "string"
            },
            "required": true,
            "name": "id",
            "in": "path"
          },
          {
            "schema": {
              "type": "string"
            },
            "required": true,
            "name": "version",
            "in": "path"
          }
        ],
        "responses": {
          "200": {
            "description": "Version retrieved successfully",
            "content": {
              "application/json": {
                "schema": {
                  "type": "object",
                  "properties": {
                    "id": {
                      "type": "string"
                    },
                    "rule_id": {
                      "type": "string"
                    },
                    "version_number": {
                      "type": "string"
                    },
                    "changelog": {
                      "type": "string"
                    },
                    "content": {
                      "type": "string"
                    },
                    "created_at": {
                      "type": "number"
                    },
                    "created_by": {
                      "type": "object",
                      "properties": {
                        "id": {
                          "type": "string"
                        },
                        "username": {
                          "type": "string"
                        }
                      },
                      "required": [
                        "id",
                        "username"
                      ]
                    }
                  },
                  "required": [
                    "id",
                    "rule_id",
                    "version_number",
                    "content",
                    "created_at",
                    "created_by"
                  ]
                }
              }
            }
          },
          "401": {
            "description": "Unauthorized"
          },
          "404": {
            "description": "Rule or version not found"
          }
        }
      }
    },
    "/rules/{id}/diff": {
      "get": {
        "tags": [
          "Rules",
          "Versions"
        ],
        "summary": "Get diff between two versions of a rule",
        "security": [
          {
            "bearerAuth": []
          }
        ],
        "operationId": "get_DiffVersionsEndpoint",
        "parameters": [
          {
            "schema": {
              "type": "string"
            },
            "required": true,
            "name": "id",
            "in": "path"
          },
          {
            "schema": {
              "type": "string"
            },
            "required": true,
            "name": "from",
            "in": "query"
          },
          {
            "schema": {
              "type": "string"
            },
            "required": true,
            "name": "to",
            "in": "query"
          }
        ],
        "responses": {
          "200": {
            "description": "Diff retrieved successfully",
            "content": {
              "application/json": {
                "schema": {
                  "type": "object",
                  "properties": {
                    "from_version": {
                      "type": "string"
                    },
                    "to_version": {
                      "type": "string"
                    },
                    "from_content": {
                      "type": "string"
                    },
                    "to_content": {
                      "type": "string"
                    },
                    "changes": {
                      "type": "object",
                      "properties": {
                        "additions": {
                          "type": "number"
                        },
                        "deletions": {
                          "type": "number"
                        }
                      },
                      "required": [
                        "additions",
                        "deletions"
                      ]
                    }
                  },
                  "required": [
                    "from_version",
                    "to_version",
                    "from_content",
                    "to_content",
                    "changes"
                  ]
                }
              }
            }
          },
          "401": {
            "description": "Unauthorized"
          },
          "404": {
            "description": "Rule or version not found"
          }
        }
      }
    },
    "/teams": {
      "post": {
        "tags": [
          "Teams"
        ],
        "summary": "Create a new team",
        "security": [
          {
            "bearerAuth": []
          }
        ],
        "operationId": "post_CreateTeamEndpoint",
        "requestBody": {
          "content": {
            "application/json": {
              "schema": {
                "type": "object",
                "properties": {
                  "name": {
                    "type": "string",
                    "minLength": 1,
                    "maxLength": 50,
                    "pattern": "^[a-zA-Z0-9-_]+$"
                  },
                  "display_name": {
                    "type": "string",
                    "minLength": 1,
                    "maxLength": 100
                  },
                  "description": {
                    "type": "string",
                    "maxLength": 500
                  }
                },
                "required": [
                  "name",
                  "display_name"
                ]
              }
            }
          }
        },
        "responses": {
          "201": {
            "description": "Team created successfully",
            "content": {
              "application/json": {
                "schema": {
                  "type": "object",
                  "properties": {
                    "id": {
                      "type": "string"
                    },
                    "name": {
                      "type": "string"
                    },
                    "display_name": {
                      "type": "string"
                    },
                    "description": {
                      "type": [
                        "string",
                        "null"
                      ]
                    },
                    "owner_id": {
                      "type": "string"
                    },
                    "created_at": {
                      "type": "number"
                    },
                    "updated_at": {
                      "type": "number"
                    }
                  },
                  "required": [
                    "id",
                    "name",
                    "display_name",
                    "description",
                    "owner_id",
                    "created_at",
                    "updated_at"
                  ]
                }
              }
            }
          },
          "400": {
            "description": "Invalid input data"
          },
          "401": {
            "description": "Authentication required"
          },
          "409": {
            "description": "Team name already exists"
          }
        }
      },
      "get": {
        "tags": [
          "Teams"
        ],
        "summary": "Get teams for current user",
        "security": [
          {
            "bearerAuth": []
          }
        ],
        "operationId": "get_GetTeamsEndpoint",
        "parameters": [
          {
            "schema": {
              "type": "string",
              "default": "20"
            },
            "required": false,
            "name": "limit",
            "in": "query"
          },
          {
            "schema": {
              "type": "string",
              "default": "0"
            },
            "required": false,
            "name": "offset",
            "in": "query"
          }
        ],
        "responses": {
          "200": {
            "description": "Teams retrieved successfully",
            "content": {
              "application/json": {
                "schema": {
                  "type": "object",
                  "properties": {
                    "results": {
                      "type": "array",
                      "items": {
                        "type": "object",
                        "properties": {
                          "id": {
                            "type": "string"
                          },
                          "name": {
                            "type": "string"
                          },
                          "display_name": {
                            "type": "string"
                          },
                          "description": {
                            "type": [
                              "string",
                              "null"
                            ]
                          },
                          "owner_id": {
                            "type": "string"
                          },
                          "created_at": {
                            "type": "number"
                          },
                          "updated_at": {
                            "type": "number"
                          },
                          "role": {
                            "type": "string"
                          },
                          "member_count": {
                            "type": "number"
                          }
                        },
                        "required": [
                          "id",
                          "name",
                          "display_name",
                          "description",
                          "owner_id",
                          "created_at",
                          "updated_at",
                          "role",
                          "member_count"
                        ]
                      }
                    },
                    "total": {
                      "type": "number"
                    },
                    "limit": {
                      "type": "number"
                    },
                    "offset": {
                      "type": "number"
                    }
                  },
                  "required": [
                    "results",
                    "total",
                    "limit",
                    "offset"
                  ]
                }
              }
            }
          },
          "401": {
            "description": "Authentication required"
          }
        }
      }
    },
    "/teams/{id}": {
      "get": {
        "tags": [
          "Teams"
        ],
        "summary": "Get team details",
        "security": [
          {
            "bearerAuth": []
          }
        ],
        "operationId": "get_GetTeamEndpoint",
        "parameters": [
          {
            "schema": {
              "type": "string"
            },
            "required": true,
            "name": "id",
            "in": "path"
          }
        ],
        "responses": {
          "200": {
            "description": "Team details retrieved successfully",
            "content": {
              "application/json": {
                "schema": {
                  "type": "object",
                  "properties": {
                    "id": {
                      "type": "string"
                    },
                    "name": {
                      "type": "string"
                    },
                    "display_name": {
                      "type": "string"
                    },
                    "description": {
                      "type": [
                        "string",
                        "null"
                      ]
                    },
                    "owner_id": {
                      "type": "string"
                    },
                    "created_at": {
                      "type": "number"
                    },
                    "updated_at": {
                      "type": "number"
                    },
                    "role": {
                      "type": "string"
                    },
                    "members": {
                      "type": "array",
                      "items": {
                        "type": "object",
                        "properties": {
                          "user_id": {
                            "type": "string"
                          },
                          "username": {
                            "type": "string"
                          },
                          "email": {
                            "type": "string"
                          },
                          "role": {
                            "type": "string"
                          },
                          "joined_at": {
                            "type": "number"
                          }
                        },
                        "required": [
                          "user_id",
                          "username",
                          "email",
                          "role",
                          "joined_at"
                        ]
                      }
                    },
                    "rule_count": {
                      "type": "number"
                    }
                  },
                  "required": [
                    "id",
                    "name",
                    "display_name",
                    "description",
                    "owner_id",
                    "created_at",
                    "updated_at",
                    "role",
                    "members",
                    "rule_count"
                  ]
                }
              }
            }
          },
          "401": {
            "description": "Authentication required"
          },
          "403": {
            "description": "Not a member of this team"
          },
          "404": {
            "description": "Team not found"
          }
        }
      },
      "put": {
        "tags": [
          "Teams"
        ],
        "summary": "Update team details",
        "security": [
          {
            "bearerAuth": []
          }
        ],
        "operationId": "put_UpdateTeamEndpoint",
        "parameters": [
          {
            "schema": {
              "type": "string"
            },
            "required": true,
            "name": "id",
            "in": "path"
          }
        ],
        "requestBody": {
          "content": {
            "application/json": {
              "schema": {
                "type": "object",
                "properties": {
                  "name": {
                    "type": "string",
                    "minLength": 1,
                    "maxLength": 50,
                    "pattern": "^[a-zA-Z0-9-_]+$"
                  },
                  "display_name": {
                    "type": "string",
                    "minLength": 1,
                    "maxLength": 100
                  },
                  "description": {
                    "type": "string",
                    "maxLength": 500
                  }
                }
              }
            }
          }
        },
        "responses": {
          "200": {
            "description": "Team updated successfully",
            "content": {
              "application/json": {
                "schema": {
                  "type": "object",
                  "properties": {
                    "id": {
                      "type": "string"
                    },
                    "name": {
                      "type": "string"
                    },
                    "display_name": {
                      "type": "string"
                    },
                    "description": {
                      "type": [
                        "string",
                        "null"
                      ]
                    },
                    "owner_id": {
                      "type": "string"
                    },
                    "created_at": {
                      "type": "number"
                    },
                    "updated_at": {
                      "type": "number"
                    }
                  },
                  "required": [
                    "id",
                    "name",
                    "display_name",
                    "description",
                    "owner_id",
                    "created_at",
                    "updated_at"
                  ]
                }
              }
            }
          },
          "400": {
            "description": "Invalid input data"
          },
          "401": {
            "description": "Authentication required"
          },
          "403": {
            "description": "Not authorized to update this team"
          },
          "404": {
            "description": "Team not found"
          },
          "409": {
            "description": "Team name already exists"
          }
        }
      },
      "delete": {
        "tags": [
          "Teams"
        ],
        "summary": "Delete team",
        "security": [
          {
            "bearerAuth": []
          }
        ],
        "operationId": "delete_DeleteTeamEndpoint",
        "parameters": [
          {
            "schema": {
              "type": "string"
            },
            "required": true,
            "name": "id",
            "in": "path"
          }
        ],
        "responses": {
          "204": {
            "description": "Team deleted successfully"
          },
          "401": {
            "description": "Authentication required"
          },
          "403": {
            "description": "Not authorized to delete this team"
          },
          "404": {
            "description": "Team not found"
          }
        }
      }
    },
    "/teams/{id}/members": {
      "post": {
        "tags": [
          "Teams"
        ],
        "summary": "Add member to team",
        "security": [
          {
            "bearerAuth": []
          }
        ],
        "operationId": "post_AddTeamMemberEndpoint",
        "parameters": [
          {
            "schema": {
              "type": "string"
            },
            "required": true,
            "name": "id",
            "in": "path"
          }
        ],
        "requestBody": {
          "content": {
            "application/json": {
              "schema": {
                "type": "object",
                "properties": {
                  "user_id": {
                    "type": "string"
                  },
                  "role": {
                    "type": "string",
                    "enum": [
                      "admin",
                      "member"
                    ],
                    "default": "member"
                  }
                },
                "required": [
                  "user_id"
                ]
              }
            }
          }
        },
        "responses": {
          "201": {
            "description": "Member added successfully",
            "content": {
              "application/json": {
                "schema": {
                  "type": "object",
                  "properties": {
                    "user_id": {
                      "type": "string"
                    },
                    "username": {
                      "type": "string"
                    },
                    "email": {
                      "type": "string"
                    },
                    "role": {
                      "type": "string"
                    },
                    "joined_at": {
                      "type": "number"
                    }
                  },
                  "required": [
                    "user_id",
                    "username",
                    "email",
                    "role",
                    "joined_at"
                  ]
                }
              }
            }
          },
          "400": {
            "description": "Invalid input data"
          },
          "401": {
            "description": "Authentication required"
          },
          "403": {
            "description": "Not authorized to add members"
          },
          "404": {
            "description": "Team or user not found"
          },
          "409": {
            "description": "User is already a member"
          }
        }
      }
    },
    "/teams/{id}/members/{userId}": {
      "delete": {
        "tags": [
          "Teams"
        ],
        "summary": "Remove member from team",
        "security": [
          {
            "bearerAuth": []
          }
        ],
        "operationId": "delete_RemoveTeamMemberEndpoint",
        "parameters": [
          {
            "schema": {
              "type": "string"
            },
            "required": true,
            "name": "id",
            "in": "path"
          },
          {
            "schema": {
              "type": "string"
            },
            "required": true,
            "name": "userId",
            "in": "path"
          }
        ],
        "responses": {
          "204": {
            "description": "Member removed successfully"
          },
          "401": {
            "description": "Authentication required"
          },
          "403": {
            "description": "Not authorized to remove members"
          },
          "404": {
            "description": "Team or member not found"
          }
        }
      },
      "put": {
        "tags": [
          "Teams"
        ],
        "summary": "Update team member role",
        "security": [
          {
            "bearerAuth": []
          }
        ],
        "operationId": "put_UpdateTeamMemberEndpoint",
        "parameters": [
          {
            "schema": {
              "type": "string"
            },
            "required": true,
            "name": "id",
            "in": "path"
          },
          {
            "schema": {
              "type": "string"
            },
            "required": true,
            "name": "userId",
            "in": "path"
          }
        ],
        "requestBody": {
          "content": {
            "application/json": {
              "schema": {
                "type": "object",
                "properties": {
                  "role": {
                    "type": "string",
                    "enum": [
                      "admin",
                      "member"
                    ]
                  }
                },
                "required": [
                  "role"
                ]
              }
            }
          }
        },
        "responses": {
          "200": {
            "description": "Member role updated successfully",
            "content": {
              "application/json": {
                "schema": {
                  "type": "object",
                  "properties": {
                    "user_id": {
                      "type": "string"
                    },
                    "username": {
                      "type": "string"
                    },
                    "email": {
                      "type": "string"
                    },
                    "role": {
                      "type": "string"
                    },
                    "joined_at": {
                      "type": "number"
                    }
                  },
                  "required": [
                    "user_id",
                    "username",
                    "email",
                    "role",
                    "joined_at"
                  ]
                }
              }
            }
          },
          "400": {
            "description": "Invalid input data"
          },
          "401": {
            "description": "Authentication required"
          },
          "403": {
            "description": "Not authorized to update member roles"
          },
          "404": {
            "description": "Team or member not found"
          }
        }
      }
    },
    "/users/profile": {
      "get": {
        "tags": [
          "Users"
        ],
        "summary": "Get current user profile",
        "security": [
          {
            "bearerAuth": []
          }
        ],
        "operationId": "get_GetProfileEndpoint",
        "responses": {
          "200": {
            "description": "User profile retrieved successfully",
            "content": {
              "application/json": {
                "schema": {
                  "type": "object",
                  "properties": {
                    "id": {
                      "type": "string"
                    },
                    "email": {
                      "type": "string"
                    },
                    "username": {
                      "type": "string"
                    },
                    "created_at": {
                      "type": "number"
                    },
                    "updated_at": {
                      "type": "number"
                    }
                  },
                  "required": [
                    "id",
                    "email",
                    "username",
                    "created_at",
                    "updated_at"
                  ]
                }
              }
            }
          },
          "401": {
            "description": "Authentication required"
          }
        }
      },
      "put": {
        "tags": [
          "Users"
        ],
        "summary": "Update current user profile",
        "security": [
          {
            "bearerAuth": []
          }
        ],
        "operationId": "put_UpdateProfileEndpoint",
        "requestBody": {
          "content": {
            "application/json": {
              "schema": {
                "type": "object",
                "properties": {
                  "email": {
                    "type": "string",
                    "format": "email"
                  },
                  "username": {
                    "type": "string",
                    "minLength": 3,
                    "maxLength": 50,
                    "pattern": "^[a-zA-Z0-9_-]+$"
                  }
                }
              }
            }
          }
        },
        "responses": {
          "200": {
            "description": "Profile updated successfully",
            "content": {
              "application/json": {
                "schema": {
                  "type": "object",
                  "properties": {
                    "id": {
                      "type": "string"
                    },
                    "email": {
                      "type": "string"
                    },
                    "username": {
                      "type": "string"
                    },
                    "created_at": {
                      "type": "number"
                    },
                    "updated_at": {
                      "type": "number"
                    }
                  },
                  "required": [
                    "id",
                    "email",
                    "username",
                    "created_at",
                    "updated_at"
                  ]
                }
              }
            }
          },
          "400": {
            "description": "Invalid input data"
          },
          "401": {
            "description": "Authentication required"
          },
          "409": {
            "description": "Email or username already exists"
          }
        }
      }
    },
    "/users/settings": {
      "get": {
        "tags": [
          "Users"
        ],
        "summary": "Get current user settings",
        "security": [
          {
            "bearerAuth": []
          }
        ],
        "operationId": "get_GetSettingsEndpoint",
        "responses": {
          "200": {
            "description": "User settings retrieved successfully",
            "content": {
              "application/json": {
                "schema": {
                  "type": "object",
                  "properties": {
                    "locale": {
                      "type": "string",
                      "default": "en"
                    },
                    "theme": {
                      "type": "string",
                      "default": "light"
                    },
                    "timezone": {
                      "type": "string",
                      "default": "UTC"
                    },
                    "notifications": {
                      "type": "object",
                      "properties": {
                        "email": {
                          "type": "boolean",
                          "default": true
                        },
                        "push": {
                          "type": "boolean",
                          "default": true
                        }
                      },
                      "default": {
                        "email": true,
                        "push": true
                      }
                    }
                  }
                }
              }
            }
          },
          "401": {
            "description": "Authentication required"
          }
        }
      },
      "put": {
        "tags": [
          "Users"
        ],
        "summary": "Update current user settings",
        "security": [
          {
            "bearerAuth": []
          }
        ],
        "operationId": "put_UpdateSettingsEndpoint",
        "requestBody": {
          "content": {
            "application/json": {
              "schema": {
                "type": "object",
                "properties": {
                  "locale": {
                    "type": "string"
                  },
                  "theme": {
                    "type": "string",
                    "enum": [
                      "light",
                      "dark",
                      "system"
                    ]
                  },
                  "timezone": {
                    "type": "string"
                  },
                  "notifications": {
                    "type": "object",
                    "properties": {
                      "email": {
                        "type": "boolean"
                      },
                      "push": {
                        "type": "boolean"
                      }
                    }
                  }
                }
              }
            }
          }
        },
        "responses": {
          "200": {
            "description": "Settings updated successfully",
            "content": {
              "application/json": {
                "schema": {
                  "type": "object",
                  "properties": {
                    "locale": {
                      "type": "string"
                    },
                    "theme": {
                      "type": "string"
                    },
                    "timezone": {
                      "type": "string"
                    },
                    "notifications": {
                      "type": "object",
                      "properties": {
                        "email": {
                          "type": "boolean"
                        },
                        "push": {
                          "type": "boolean"
                        }
                      },
                      "required": [
                        "email",
                        "push"
                      ]
                    }
                  },
                  "required": [
                    "locale",
                    "theme",
                    "timezone",
                    "notifications"
                  ]
                }
              }
            }
          },
          "400": {
            "description": "Invalid input data"
          },
          "401": {
            "description": "Authentication required"
          }
        }
      }
    }
  },
  "webhooks": {}
}